pyRobustRegressionLib/__init__.py
pyRobustRegressionLib-1.3.2.data/data/lib/RobustRegressionLib.dll
pyRobustRegressionLib-1.3.2.data/data/lib/RobustRegressionLib.lib
pyRobustRegressionLib-1.3.2.data/data/lib/pyRobustRegressionLib.cp312-win_amd64.pyd
pyRobustRegressionLib-1.3.2.dist-info/License
pyRobustRegressionLib-1.3.2.dist-info/METADATA
pyRobustRegressionLib-1.3.2.dist-info/WHEEL
pyRobustRegressionLib-1.3.2.dist-info/top_level.txt
pyRobustRegressionLib-1.3.2.dist-info/RECORD
