Metadata-Version: 2.1
Name: pyRobustRegressionLib
Version: 1.3.2
Summary: A library that implements algorithms for linear and non-linear robust regression.
Home-page: https://github.com/bschulz81/robustregression
Author: Benjamin Schulz
License: MIT License
Keywords: robust regression,forward-search,Huber's loss function,repeated median regression,simple linear regression,non-linear regression,Levenberg-Marquardt algorithm,statistics,estimators,S-estimator,Q-estimator,Student T-distribution,interquartile range,machine learning
Classifier: Programming Language :: C++
Classifier: Programming Language :: Python :: 3
Classifier: License :: OSI Approved :: MIT License
Classifier: Operating System :: Microsoft
Classifier: Operating System :: POSIX
Classifier: Operating System :: MacOS
Classifier: Development Status :: 5 - Production/Stable
Classifier: Topic :: Scientific/Engineering :: Mathematics
Classifier: Topic :: Software Development :: Libraries
Classifier: Topic :: Software Development :: Libraries :: Python Modules
Classifier: Intended Audience :: Science/Research
Classifier: Intended Audience :: Education
Classifier: Intended Audience :: Developers
Requires-Python: >=3.7
License-File: License
